<?xml version="1.0" encoding="UTF-8"?>
<gmi:MI_Metadata xmlns:gmi="http://www.isotc211.org/2005/gmi"
                 xmlns:gco="http://www.isotc211.org/2005/gco"
                 xmlns:gmd="http://www.isotc211.org/2005/gmd"
                 xmlns:gml="http://www.opengis.net/gml/3.2"
                 xmlns:gmx="http://www.isotc211.org/2005/gmx"
                 xmlns:gsr="http://www.isotc211.org/2005/gsr"
                 xmlns:gss="http://www.isotc211.org/2005/gss"
                 xmlns:gts="http://www.isotc211.org/2005/gts"
                 xmlns:xlink="http://www.w3.org/1999/xlink"
                 xmlns:xsi="http://www.w3.org/2001/XMLSchema-instance"
                 xsi:schemaLocation="http://www.isotc211.org/2005/gmi https://data.noaa.gov/resources/iso19139/schema.xsd">
   <gmd:fileIdentifier>
      <gco:CharacterString>gov.noaa.ncdc:C01088</gco:CharacterString>
   </gmd:fileIdentifier>
   <gmd:language>
      <gco:CharacterString>eng; USA</gco:CharacterString>
   </gmd:language>
   <gmd:characterSet>
      <gmd:MD_CharacterSetCode codeList="https://data.noaa.gov/resources/iso19139/schema/resources/Codelist/gmxCodelists.xml#MD_CharacterSetCode"
                               codeListValue="utf8">utf8</gmd:MD_CharacterSetCode>
   </gmd:characterSet>
   <gmd:hierarchyLevel>
      <gmd:MD_ScopeCode codeList="https://data.noaa.gov/resources/iso19139/schema/resources/Codelist/gmxCodelists.xml#MD_ScopeCode"
                        codeListValue="dataset">dataset</gmd:MD_ScopeCode>
   </gmd:hierarchyLevel>
   <gmd:contact>
      <gmd:CI_ResponsibleParty>
         <gmd:organisationName>
            <gco:CharacterString>DOC/NOAA/NESDIS/NCEI &gt; National Centers for Environmental Information, NESDIS, NOAA, U.S. Department of Commerce</gco:CharacterString>
         </gmd:organisationName>
         <gmd:positionName>
            <gco:CharacterString>ISO 19115 Metadata Contact</gco:CharacterString>
         </gmd:positionName>
         <gmd:contactInfo>
            <gmd:CI_Contact>
               <gmd:phone>
                  <gmd:CI_Telephone>
                     <gmd:voice>
                        <gco:CharacterString>1-828-271-4800</gco:CharacterString>
                     </gmd:voice>
                     <gmd:facsimile>
                        <gco:CharacterString>1-828-271-4876</gco:CharacterString>
                     </gmd:facsimile>
                  </gmd:CI_Telephone>
               </gmd:phone>
               <gmd:address>
                  <gmd:CI_Address>
                     <gmd:deliveryPoint>
                        <gco:CharacterString>151 Patton Avenue</gco:CharacterString>
                     </gmd:deliveryPoint>
                     <gmd:deliveryPoint>
                        <gco:CharacterString>Veach-Baley Federal Building, Room 468</gco:CharacterString>
                     </gmd:deliveryPoint>
                     <gmd:city>
                        <gco:CharacterString>Asheville</gco:CharacterString>
                     </gmd:city>
                     <gmd:administrativeArea>
                        <gco:CharacterString>NC</gco:CharacterString>
                     </gmd:administrativeArea>
                     <gmd:postalCode>
                        <gco:CharacterString>28801-5001</gco:CharacterString>
                     </gmd:postalCode>
                     <gmd:country>
                        <gco:CharacterString>USA</gco:CharacterString>
                     </gmd:country>
                     <gmd:electronicMailAddress>
                        <gco:CharacterString>ncei.orders@noaa.gov</gco:CharacterString>
                     </gmd:electronicMailAddress>
                  </gmd:CI_Address>
               </gmd:address>
               <gmd:onlineResource>
                  <gmd:CI_OnlineResource>
                     <gmd:linkage>
                        <gmd:URL>https://www.ncei.noaa.gov</gmd:URL>
                     </gmd:linkage>
                     <gmd:protocol>
                        <gco:CharacterString>HTTPS</gco:CharacterString>
                     </gmd:protocol>
                     <gmd:applicationProfile>
                        <gco:CharacterString>Web Browser</gco:CharacterString>
                     </gmd:applicationProfile>
                     <gmd:name>
                        <gco:CharacterString>NOAA National Centers for Environmental Information (NCEI)</gco:CharacterString>
                     </gmd:name>
                     <gmd:description>
                        <gco:CharacterString>NCEI home page with information, data access and contact information.</gco:CharacterString>
                     </gmd:description>
                     <gmd:function>
                        <gmd:CI_OnLineFunctionCode codeList="https://data.noaa.gov/resources/iso19139/schema/resources/Codelist/gmxCodelists.xml#CI_OnLineFunctionCode"
                                                   codeListValue="information">information</gmd:CI_OnLineFunctionCode>
                     </gmd:function>
                  </gmd:CI_OnlineResource>
               </gmd:onlineResource>
               <gmd:hoursOfService>
                  <gco:CharacterString>8:00 - 6:00 Eastern</gco:CharacterString>
               </gmd:hoursOfService>
            </gmd:CI_Contact>
         </gmd:contactInfo>
         <gmd:role>
            <gmd:CI_RoleCode codeList="https://data.noaa.gov/resources/iso19139/schema/resources/Codelist/gmxCodelists.xml#CI_RoleCode"
                             codeListValue="pointOfContact">pointOfContact</gmd:CI_RoleCode>
         </gmd:role>
      </gmd:CI_ResponsibleParty>
   </gmd:contact>
   <gmd:dateStamp>
      <gco:Date>2018-05-25</gco:Date>
   </gmd:dateStamp>
   <gmd:metadataStandardName>
      <gco:CharacterString>ISO 19115-2 Geographic Information - Metadata - Part 2: Extensions for Imagery and Gridded Data</gco:CharacterString>
   </gmd:metadataStandardName>
   <gmd:metadataStandardVersion>
      <gco:CharacterString>ISO 19115-2:2009(E)</gco:CharacterString>
   </gmd:metadataStandardVersion>
   <gmd:identificationInfo>
      <gmd:MD_DataIdentification>
         <gmd:citation>
            <gmd:CI_Citation>
               <gmd:title>
                  <gco:CharacterString>Surface Observations from Punta Arenas, Chile</gco:CharacterString>
               </gmd:title>
               <gmd:alternateTitle>
                  <gco:CharacterString>EV2 - Chile</gco:CharacterString>
               </gmd:alternateTitle>
               <gmd:date>
                  <gmd:CI_Date>
                     <gmd:date>
                        <gco:Date>2011-03-15</gco:Date>
                     </gmd:date>
                     <gmd:dateType>
                        <gmd:CI_DateTypeCode codeList="https://data.noaa.gov/resources/iso19139/schema/resources/Codelist/gmxCodelists.xml#CI_DateTypeCode"
                                             codeListValue="publication">publication</gmd:CI_DateTypeCode>
                     </gmd:dateType>
                  </gmd:CI_Date>
               </gmd:date>
               <gmd:date>
                  <gmd:CI_Date>
                     <gmd:date>
                        <gco:Date>2013-05-02</gco:Date>
                     </gmd:date>
                     <gmd:dateType>
                        <gmd:CI_DateTypeCode codeList="https://data.noaa.gov/resources/iso19139/schema/resources/Codelist/gmxCodelists.xml#CI_DateTypeCode"
                                             codeListValue="revision">revision</gmd:CI_DateTypeCode>
                     </gmd:dateType>
                  </gmd:CI_Date>
               </gmd:date>
               <gmd:identifier>
                  <gmd:MD_Identifier>
                     <gmd:code>
                        <gco:CharacterString>NCEI DSI 3900_01</gco:CharacterString>
                     </gmd:code>
                  </gmd:MD_Identifier>
               </gmd:identifier>
               <gmd:identifier>
                  <gmd:MD_Identifier>
                     <gmd:code>
                        <gco:CharacterString>gov.noaa.ncdc:C01088</gco:CharacterString>
                     </gmd:code>
                  </gmd:MD_Identifier>
               </gmd:identifier>
               <gmd:citedResponsibleParty>
                  <gmd:CI_ResponsibleParty>
                     <gmd:organisationName>
                        <gco:CharacterString>DOC/NOAA/NESDIS/NCEI &gt; National Centers for Environmental Information, NESDIS, NOAA, U.S. Department of Commerce</gco:CharacterString>
                     </gmd:organisationName>
                     <gmd:role>
                        <gmd:CI_RoleCode codeList="https://data.noaa.gov/resources/iso19139/schema/resources/Codelist/gmxCodelists.xml#CI_RoleCode"
                                         codeListValue="publisher">publisher</gmd:CI_RoleCode>
                     </gmd:role>
                  </gmd:CI_ResponsibleParty>
               </gmd:citedResponsibleParty>
               <gmd:citedResponsibleParty>
                  <gmd:CI_ResponsibleParty>
                     <gmd:organisationName>
                        <gco:CharacterString>DOC/NOAA/NESDIS/NCDC &gt; National Climatic Data Center, NESDIS, NOAA, U.S. Department of Commerce</gco:CharacterString>
                     </gmd:organisationName>
                     <gmd:positionName>
                        <gco:CharacterString>User Engagement and Services Branch</gco:CharacterString>
                     </gmd:positionName>
                     <gmd:contactInfo>
                        <gmd:CI_Contact>
                           <gmd:phone>
                              <gmd:CI_Telephone>
                                 <gmd:voice>
                                    <gco:CharacterString>+1 (828) 271-4800</gco:CharacterString>
                                 </gmd:voice>
                                 <gmd:facsimile>
                                    <gco:CharacterString>+1 (828) 271-4876</gco:CharacterString>
                                 </gmd:facsimile>
                              </gmd:CI_Telephone>
                           </gmd:phone>
                           <gmd:address>
                              <gmd:CI_Address>
                                 <gmd:deliveryPoint>
                                    <gco:CharacterString>151 Patton Avenue</gco:CharacterString>
                                 </gmd:deliveryPoint>
                                 <gmd:deliveryPoint>
                                    <gco:CharacterString>Veach-Baley Federal Building, Room 468</gco:CharacterString>
                                 </gmd:deliveryPoint>
                                 <gmd:city>
                                    <gco:CharacterString>Asheville</gco:CharacterString>
                                 </gmd:city>
                                 <gmd:administrativeArea>
                                    <gco:CharacterString>NC</gco:CharacterString>
                                 </gmd:administrativeArea>
                                 <gmd:postalCode>
                                    <gco:CharacterString>28801-5001</gco:CharacterString>
                                 </gmd:postalCode>
                                 <gmd:country>
                                    <gco:CharacterString>USA</gco:CharacterString>
                                 </gmd:country>
                                 <gmd:electronicMailAddress>
                                    <gco:CharacterString>ncei.orders@noaa.gov</gco:CharacterString>
                                 </gmd:electronicMailAddress>
                              </gmd:CI_Address>
                           </gmd:address>
                           <gmd:hoursOfService>
                              <gco:CharacterString>8:00 - 6:00 Eastern</gco:CharacterString>
                           </gmd:hoursOfService>
                        </gmd:CI_Contact>
                     </gmd:contactInfo>
                     <gmd:role>
                        <gmd:CI_RoleCode codeList="https://data.noaa.gov/resources/iso19139/schema/resources/Codelist/gmxCodelists.xml#CI_RoleCode"
                                         codeListValue="publisher">publisher</gmd:CI_RoleCode>
                     </gmd:role>
                  </gmd:CI_ResponsibleParty>
               </gmd:citedResponsibleParty>
               <gmd:citedResponsibleParty>
                  <gmd:CI_ResponsibleParty>
                     <gmd:organisationName gco:nilReason="missing"/>
                     <gmd:contactInfo>
                        <gmd:CI_Contact>
                           <gmd:onlineResource>
                              <gmd:CI_OnlineResource>
                                 <gmd:linkage>
                                    <gmd:URL>https://www.ncdc.noaa.gov/climate-information/research-programs/climate-database-modernization-program</gmd:URL>
                                 </gmd:linkage>
                                 <gmd:protocol>
                                    <gco:CharacterString>HTTPS</gco:CharacterString>
                                 </gmd:protocol>
                                 <gmd:applicationProfile>
                                    <gco:CharacterString>Web Browser</gco:CharacterString>
                                 </gmd:applicationProfile>
                                 <gmd:name>
                                    <gco:CharacterString>CDMP Web site</gco:CharacterString>
                                 </gmd:name>
                                 <gmd:description>
                                    <gco:CharacterString>Information about the Climate Database Modernization Program (CDMP) and the current Image Access Repository.</gco:CharacterString>
                                 </gmd:description>
                                 <gmd:function>
                                    <gmd:CI_OnLineFunctionCode codeList="https://data.noaa.gov/resources/iso19139/schema/resources/Codelist/gmxCodelists.xml#CI_OnLineFunctionCode"
                                                               codeListValue="information">information</gmd:CI_OnLineFunctionCode>
                                 </gmd:function>
                              </gmd:CI_OnlineResource>
                           </gmd:onlineResource>
                        </gmd:CI_Contact>
                     </gmd:contactInfo>
                     <gmd:role gco:nilReason="missing"/>
                  </gmd:CI_ResponsibleParty>
               </gmd:citedResponsibleParty>
               <gmd:presentationForm>
                  <gmd:CI_PresentationFormCode codeList="https://data.noaa.gov/resources/iso19139/schema/resources/Codelist/gmxCodelists.xml#CI_PresentationFormCode"
                                               codeListValue="imageDigital">imageDigital</gmd:CI_PresentationFormCode>
               </gmd:presentationForm>
            </gmd:CI_Citation>
         </gmd:citation>
         <gmd:abstract>
            <gco:CharacterString>Surface Observations from Punta Arenas, in extreme southern Chile. WMO station ID 85934. Period of record 1896-1954. The original forms were scanned at the Museo Salesiano Maggiorino Borgatello, a private regional museum in Punta Arenas with funding provided by NOAA through the Environmental Services Data and Information Management (ESDIM) program carryover. However, since the Museum is a private organization not affiliated with the Chilean government or its agencies, its directors required an agreement with a non-profit organization in order for them to agree to allow NOAA to digitize their data and to make those digitized data free and unrestricted to the world community. This effort required some discretion as well as the intervention of a non-profit since the museum specifically expressed a desire not to work with the Chilean national meteorological service. CD-ROMs containing the images were sent to NCDC via the National Weather Service International Activities Office. A CDMP keying task was completed in 2006-07 to key and ingest data from 1896-1941 into digital data sets. This period had a consistent format, with one image for each ten-day period in each month</gco:CharacterString>
         </gmd:abstract>
         <gmd:purpose>
            <gco:CharacterString>In the late 1990s NCDC realized the need to host digital images of weather and climate records on the internet. As a result, EV2 was developed as a key system for providing access to the millions of original source data images in the NCDC archives. With its upload and index capability, EV2 also enables the continuation of NCDC's commitment to make more of its weather and climate data available online so that users across the world can view climate and weather records held in the NCDC archives.</gco:CharacterString>
         </gmd:purpose>
         <gmd:credit>
            <gco:CharacterString/>
         </gmd:credit>
         <gmd:status>
            <gmd:MD_ProgressCode codeList="https://data.noaa.gov/resources/iso19139/schema/resources/Codelist/gmxCodelists.xml#MD_ProgressCode"
                                 codeListValue="completed">completed</gmd:MD_ProgressCode>
         </gmd:status>
         <gmd:pointOfContact>
            <gmd:CI_ResponsibleParty>
               <gmd:individualName>
                  <gco:CharacterString>Jason Cooper</gco:CharacterString>
               </gmd:individualName>
               <gmd:organisationName>
                  <gco:CharacterString>DOC/NOAA/NESDIS/NCEI &gt; National Centers for Environmental Information, NESDIS, NOAA, U.S. Department of Commerce</gco:CharacterString>
               </gmd:organisationName>
               <gmd:positionName>
                  <gco:CharacterString>NCDC Archivist</gco:CharacterString>
               </gmd:positionName>
               <gmd:contactInfo>
                  <gmd:CI_Contact>
                     <gmd:phone>
                        <gmd:CI_Telephone>
                           <gmd:voice>
                              <gco:CharacterString>+1 828-271-4800</gco:CharacterString>
                           </gmd:voice>
                           <gmd:facsimile>
                              <gco:CharacterString>+1 828-271-4876</gco:CharacterString>
                           </gmd:facsimile>
                        </gmd:CI_Telephone>
                     </gmd:phone>
                     <gmd:address>
                        <gmd:CI_Address>
                           <gmd:deliveryPoint>
                              <gco:CharacterString>Federal Building, Room 468</gco:CharacterString>
                           </gmd:deliveryPoint>
                           <gmd:deliveryPoint>
                              <gco:CharacterString>151 Patton Avenue</gco:CharacterString>
                           </gmd:deliveryPoint>
                           <gmd:city>
                              <gco:CharacterString>Asheville</gco:CharacterString>
                           </gmd:city>
                           <gmd:administrativeArea>
                              <gco:CharacterString>NC</gco:CharacterString>
                           </gmd:administrativeArea>
                           <gmd:postalCode>
                              <gco:CharacterString>28801-5001</gco:CharacterString>
                           </gmd:postalCode>
                           <gmd:country>
                              <gco:CharacterString>USA</gco:CharacterString>
                           </gmd:country>
                           <gmd:electronicMailAddress>
                              <gco:CharacterString>ncei.orders@noaa.gov</gco:CharacterString>
                           </gmd:electronicMailAddress>
                        </gmd:CI_Address>
                     </gmd:address>
                     <gmd:hoursOfService>
                        <gco:CharacterString>8:00 - 5:00 Eastern</gco:CharacterString>
                     </gmd:hoursOfService>
                  </gmd:CI_Contact>
               </gmd:contactInfo>
               <gmd:role>
                  <gmd:CI_RoleCode codeList="https://data.noaa.gov/resources/iso19139/schema/resources/Codelist/gmxCodelists.xml#CI_RoleCode"
                                   codeListValue="pointOfContact">pointOfContact</gmd:CI_RoleCode>
               </gmd:role>
            </gmd:CI_ResponsibleParty>
         </gmd:pointOfContact>
         <gmd:resourceMaintenance>
            <gmd:MD_MaintenanceInformation>
               <gmd:maintenanceAndUpdateFrequency>
                  <gmd:MD_MaintenanceFrequencyCode codeList="https://data.noaa.gov/resources/iso19139/schema/resources/Codelist/gmxCodelists.xml#MD_MaintenanceFrequencyCode"
                                                   codeListValue="irregular">irregular</gmd:MD_MaintenanceFrequencyCode>
               </gmd:maintenanceAndUpdateFrequency>
            </gmd:MD_MaintenanceInformation>
         </gmd:resourceMaintenance>
         <gmd:graphicOverview>
            <gmd:MD_BrowseGraphic>
               <gmd:fileName>
                  <gco:CharacterString>https://www1.ncdc.noaa.gov/pub/data/metadata/images/C01088.JPG</gco:CharacterString>
               </gmd:fileName>
               <gmd:fileDescription>
                  <gco:CharacterString>Image example</gco:CharacterString>
               </gmd:fileDescription>
               <gmd:fileType>
                  <gco:CharacterString>JPG</gco:CharacterString>
               </gmd:fileType>
            </gmd:MD_BrowseGraphic>
         </gmd:graphicOverview>
         <gmd:descriptiveKeywords>
            <gmd:MD_Keywords>
               <gmd:keyword>
                  <gco:CharacterString>Earth Science &gt; Atmosphere &gt; Atmospheric Pressure &gt; Anticyclones/Cyclones</gco:CharacterString>
               </gmd:keyword>
               <gmd:keyword>
                  <gco:CharacterString>Earth Science &gt; Atmosphere &gt; Atmospheric Pressure &gt; Pressure Anomalies</gco:CharacterString>
               </gmd:keyword>
               <gmd:keyword>
                  <gco:CharacterString>Earth Science &gt; Atmosphere &gt; Precipitation &gt; Solid Precipitation &gt; Hail</gco:CharacterString>
               </gmd:keyword>
               <gmd:keyword>
                  <gco:CharacterString>Earth Science &gt; Atmosphere &gt; Precipitation &gt; Precipitation Amount</gco:CharacterString>
               </gmd:keyword>
               <gmd:keyword>
                  <gco:CharacterString>Earth Science &gt; Atmosphere &gt; Precipitation &gt; Precipitation Anomalies</gco:CharacterString>
               </gmd:keyword>
               <gmd:keyword>
                  <gco:CharacterString>Earth Science &gt; Atmosphere &gt; Precipitation &gt; Precipitation Rate</gco:CharacterString>
               </gmd:keyword>
               <gmd:keyword>
                  <gco:CharacterString>Earth Science &gt; Atmosphere &gt; Precipitation &gt; Liquid Precipitation &gt; Rain</gco:CharacterString>
               </gmd:keyword>
               <gmd:keyword>
                  <gco:CharacterString>Earth Science &gt; Atmosphere &gt; Precipitation &gt; Solid Precipitation &gt; Ice Pellets &gt; Sleet</gco:CharacterString>
               </gmd:keyword>
               <gmd:keyword>
                  <gco:CharacterString>Earth Science &gt; Atmosphere &gt; Precipitation &gt; Solid Precipitation &gt; Snow</gco:CharacterString>
               </gmd:keyword>
               <gmd:keyword>
                  <gco:CharacterString>Earth Science &gt; Atmosphere &gt; Atmospheric Temperature &gt; Surface Temperature &gt; Air Temperature</gco:CharacterString>
               </gmd:keyword>
               <gmd:keyword>
                  <gco:CharacterString>Earth Science &gt; Atmosphere &gt; Atmospheric Temperature &gt; Surface Temperature &gt; Maximum/Minimum Temperature</gco:CharacterString>
               </gmd:keyword>
               <gmd:keyword>
                  <gco:CharacterString>Earth Science &gt; Atmosphere &gt; Atmospheric Temperature &gt; Surface Temperature</gco:CharacterString>
               </gmd:keyword>
               <gmd:keyword>
                  <gco:CharacterString>Earth Science &gt; Atmosphere &gt; Atmospheric Temperature &gt; Temperature Anomalies</gco:CharacterString>
               </gmd:keyword>
               <gmd:keyword>
                  <gco:CharacterString>Earth Science &gt; Atmosphere &gt; Atmospheric Winds &gt; Surface Winds</gco:CharacterString>
               </gmd:keyword>
               <gmd:type>
                  <gmd:MD_KeywordTypeCode codeList="https://data.noaa.gov/resources/iso19139/schema/resources/Codelist/gmxCodelists.xml#MD_KeywordTypeCode"
                                          codeListValue="theme">theme</gmd:MD_KeywordTypeCode>
               </gmd:type>
               <gmd:thesaurusName>
                  <gmd:CI_Citation>
                     <gmd:title>
                        <gco:CharacterString>Global Change Master Directory (GCMD) Science Keywords</gco:CharacterString>
                     </gmd:title>
                     <gmd:date>
                        <gmd:CI_Date>
                           <gmd:date>
                              <gco:Date>2018</gco:Date>
                           </gmd:date>
                           <gmd:dateType>
                              <gmd:CI_DateTypeCode codeList="https://data.noaa.gov/resources/iso19139/schema/resources/Codelist/gmxCodelists.xml#CI_DateTypeCode"
                                                   codeListValue="revision">revision</gmd:CI_DateTypeCode>
                           </gmd:dateType>
                        </gmd:CI_Date>
                     </gmd:date>
                     <gmd:edition>
                        <gco:CharacterString>Version 8.6</gco:CharacterString>
                     </gmd:edition>
                     <gmd:citedResponsibleParty>
                        <gmd:CI_ResponsibleParty>
                           <gmd:organisationName>
                              <gco:CharacterString>Global Change Data Center, Science and Exploration Directorate, Goddard Space Flight Center (GSFC) National Aeronautics and Space Administration (NASA)</gco:CharacterString>
                           </gmd:organisationName>
                           <gmd:contactInfo>
                              <gmd:CI_Contact>
                                 <gmd:onlineResource>
                                    <gmd:CI_OnlineResource>
                                       <gmd:linkage>
                                          <gmd:URL>https://earthdata.nasa.gov/about/gcmd/global-change-master-directory-gcmd-keywords</gmd:URL>
                                       </gmd:linkage>
                                       <gmd:protocol>
                                          <gco:CharacterString>HTTPS</gco:CharacterString>
                                       </gmd:protocol>
                                       <gmd:applicationProfile>
                                          <gco:CharacterString>Web Browser</gco:CharacterString>
                                       </gmd:applicationProfile>
                                       <gmd:name>
                                          <gco:CharacterString>Global Change Master Directory (GCMD) Keywords</gco:CharacterString>
                                       </gmd:name>
                                       <gmd:description>
                                          <gco:CharacterString>The information provided on this page seeks to define how the GCMD Keywords are structured, used and accessed. It also provides information on how users can participate in the further development of the keywords.</gco:CharacterString>
                                       </gmd:description>
                                       <gmd:function>
                                          <gmd:CI_OnLineFunctionCode codeList="https://data.noaa.gov/resources/iso19139/schema/resources/Codelist/gmxCodelists.xml#CI_OnLineFunctionCode"
                                                                     codeListValue="information">information</gmd:CI_OnLineFunctionCode>
                                       </gmd:function>
                                    </gmd:CI_OnlineResource>
                                 </gmd:onlineResource>
                              </gmd:CI_Contact>
                           </gmd:contactInfo>
                           <gmd:role>
                              <gmd:CI_RoleCode codeList="https://data.noaa.gov/resources/iso19139/schema/resources/Codelist/gmxCodelists.xml#CI_RoleCode"
                                               codeListValue="publisher">publisher</gmd:CI_RoleCode>
                           </gmd:role>
                        </gmd:CI_ResponsibleParty>
                     </gmd:citedResponsibleParty>
                  </gmd:CI_Citation>
               </gmd:thesaurusName>
            </gmd:MD_Keywords>
         </gmd:descriptiveKeywords>
         <gmd:descriptiveKeywords>
            <gmd:MD_Keywords>
               <gmd:keyword>
                  <gco:CharacterString>Atmospheric - Surface - Air Temperature</gco:CharacterString>
               </gmd:keyword>
               <gmd:keyword>
                  <gco:CharacterString>Atmospheric - Surface - Precipitation</gco:CharacterString>
               </gmd:keyword>
               <gmd:keyword>
                  <gco:CharacterString>Atmospheric - Surface - Pressure</gco:CharacterString>
               </gmd:keyword>
               <gmd:keyword>
                  <gco:CharacterString>Atmospheric - Surface - Wind Speed And Direction</gco:CharacterString>
               </gmd:keyword>
               <gmd:keyword>
                  <gco:CharacterString>Atmospheric - Upper-air - Cloud Properties</gco:CharacterString>
               </gmd:keyword>
               <gmd:type>
                  <gmd:MD_KeywordTypeCode codeList="https://data.noaa.gov/resources/iso19139/schema/resources/Codelist/gmxCodelists.xml#MD_KeywordTypeCode"
                                          codeListValue="theme">theme</gmd:MD_KeywordTypeCode>
               </gmd:type>
               <gmd:thesaurusName>
                  <gmd:CI_Citation>
                     <gmd:title>
                        <gco:CharacterString>Global Climate Observing System (GCOS) Essential Climate Variables (ECVs)</gco:CharacterString>
                     </gmd:title>
                     <gmd:date>
                        <gmd:CI_Date>
                           <gmd:date>
                              <gco:Date>2017</gco:Date>
                           </gmd:date>
                           <gmd:dateType>
                              <gmd:CI_DateTypeCode codeList="https://data.noaa.gov/resources/iso19139/schema/resources/Codelist/gmxCodelists.xml#CI_DateTypeCode"
                                                   codeListValue="publication">publication</gmd:CI_DateTypeCode>
                           </gmd:dateType>
                        </gmd:CI_Date>
                     </gmd:date>
                     <gmd:edition>
                        <gco:CharacterString>Release 2017</gco:CharacterString>
                     </gmd:edition>
                     <gmd:citedResponsibleParty>
                        <gmd:CI_ResponsibleParty>
                           <gmd:organisationName>
                              <gco:CharacterString>World Meteorological Organization, United Nations</gco:CharacterString>
                           </gmd:organisationName>
                           <gmd:contactInfo>
                              <gmd:CI_Contact>
                                 <gmd:onlineResource>
                                    <gmd:CI_OnlineResource>
                                       <gmd:linkage>
                                          <gmd:URL>https://public.wmo.int/en/programmes/global-climate-observing-system/essential-climate-variables</gmd:URL>
                                       </gmd:linkage>
                                       <gmd:protocol>
                                          <gco:CharacterString>HTTP</gco:CharacterString>
                                       </gmd:protocol>
                                       <gmd:applicationProfile>
                                          <gco:CharacterString>Information</gco:CharacterString>
                                       </gmd:applicationProfile>
                                       <gmd:name>
                                          <gco:CharacterString>GCOS Essential Climate Variables</gco:CharacterString>
                                       </gmd:name>
                                       <gmd:description>
                                          <gco:CharacterString>Overview of the GCOS Essential Climate Variables.</gco:CharacterString>
                                       </gmd:description>
                                       <gmd:function>
                                          <gmd:CI_OnLineFunctionCode codeList="https://data.noaa.gov/resources/iso19139/schema/resources/Codelist/gmxCodelists.xml#CI_OnLineFunctionCode"
                                                                     codeListValue="information">information</gmd:CI_OnLineFunctionCode>
                                       </gmd:function>
                                    </gmd:CI_OnlineResource>
                                 </gmd:onlineResource>
                              </gmd:CI_Contact>
                           </gmd:contactInfo>
                           <gmd:role>
                              <gmd:CI_RoleCode codeList="https://data.noaa.gov/resources/iso19139/schema/resources/Codelist/gmxCodelists.xml#CI_RoleCode"
                                               codeListValue="custodian">custodian</gmd:CI_RoleCode>
                           </gmd:role>
                        </gmd:CI_ResponsibleParty>
                     </gmd:citedResponsibleParty>
                  </gmd:CI_Citation>
               </gmd:thesaurusName>
            </gmd:MD_Keywords>
         </gmd:descriptiveKeywords>
         <gmd:descriptiveKeywords>
            <gmd:MD_Keywords>
               <gmd:keyword>
                  <gco:CharacterString>Continent &gt; South America &gt; Chile</gco:CharacterString>
               </gmd:keyword>
               <gmd:type>
                  <gmd:MD_KeywordTypeCode codeList="https://data.noaa.gov/resources/iso19139/schema/resources/Codelist/gmxCodelists.xml#MD_KeywordTypeCode"
                                          codeListValue="place">place</gmd:MD_KeywordTypeCode>
               </gmd:type>
               <gmd:thesaurusName>
                  <gmd:CI_Citation>
                     <gmd:title>
                        <gco:CharacterString>Global Change Master Directory (GCMD) Location Keywords</gco:CharacterString>
                     </gmd:title>
                     <gmd:date>
                        <gmd:CI_Date>
                           <gmd:date>
                              <gco:Date>2018</gco:Date>
                           </gmd:date>
                           <gmd:dateType>
                              <gmd:CI_DateTypeCode codeList="https://data.noaa.gov/resources/iso19139/schema/resources/Codelist/gmxCodelists.xml#CI_DateTypeCode"
                                                   codeListValue="revision">revision</gmd:CI_DateTypeCode>
                           </gmd:dateType>
                        </gmd:CI_Date>
                     </gmd:date>
                     <gmd:edition>
                        <gco:CharacterString>Version 8.6</gco:CharacterString>
                     </gmd:edition>
                     <gmd:citedResponsibleParty>
                        <gmd:CI_ResponsibleParty>
                           <gmd:organisationName>
                              <gco:CharacterString>Global Change Data Center, Science and Exploration Directorate, Goddard Space Flight Center (GSFC) National Aeronautics and Space Administration (NASA)</gco:CharacterString>
                           </gmd:organisationName>
                           <gmd:contactInfo>
                              <gmd:CI_Contact>
                                 <gmd:onlineResource>
                                    <gmd:CI_OnlineResource>
                                       <gmd:linkage>
                                          <gmd:URL>https://earthdata.nasa.gov/about/gcmd/global-change-master-directory-gcmd-keywords</gmd:URL>
                                       </gmd:linkage>
                                       <gmd:protocol>
                                          <gco:CharacterString>HTTPS</gco:CharacterString>
                                       </gmd:protocol>
                                       <gmd:applicationProfile>
                                          <gco:CharacterString>Web Browser</gco:CharacterString>
                                       </gmd:applicationProfile>
                                       <gmd:name>
                                          <gco:CharacterString>Global Change Master Directory (GCMD) Keywords</gco:CharacterString>
                                       </gmd:name>
                                       <gmd:description>
                                          <gco:CharacterString>The information provided on this page seeks to define how the GCMD Keywords are structured, used and accessed. It also provides information on how users can participate in the further development of the keywords.</gco:CharacterString>
                                       </gmd:description>
                                       <gmd:function>
                                          <gmd:CI_OnLineFunctionCode codeList="https://data.noaa.gov/resources/iso19139/schema/resources/Codelist/gmxCodelists.xml#CI_OnLineFunctionCode"
                                                                     codeListValue="information">information</gmd:CI_OnLineFunctionCode>
                                       </gmd:function>
                                    </gmd:CI_OnlineResource>
                                 </gmd:onlineResource>
                              </gmd:CI_Contact>
                           </gmd:contactInfo>
                           <gmd:role>
                              <gmd:CI_RoleCode codeList="https://data.noaa.gov/resources/iso19139/schema/resources/Codelist/gmxCodelists.xml#CI_RoleCode"
                                               codeListValue="publisher">publisher</gmd:CI_RoleCode>
                           </gmd:role>
                        </gmd:CI_ResponsibleParty>
                     </gmd:citedResponsibleParty>
                  </gmd:CI_Citation>
               </gmd:thesaurusName>
            </gmd:MD_Keywords>
         </gmd:descriptiveKeywords>
         <gmd:descriptiveKeywords>
            <gmd:MD_Keywords>
               <gmd:keyword>
                  <gco:CharacterString>Vertical Location &gt; Land Surface</gco:CharacterString>
               </gmd:keyword>
               <gmd:type>
                  <gmd:MD_KeywordTypeCode codeList="https://data.noaa.gov/resources/iso19139/schema/resources/Codelist/gmxCodelists.xml#MD_KeywordTypeCode"
                                          codeListValue="stratum">stratum</gmd:MD_KeywordTypeCode>
               </gmd:type>
               <gmd:thesaurusName>
                  <gmd:CI_Citation>
                     <gmd:title>
                        <gco:CharacterString>Global Change Master Directory (GCMD) Location Keywords</gco:CharacterString>
                     </gmd:title>
                     <gmd:date>
                        <gmd:CI_Date>
                           <gmd:date>
                              <gco:Date>2018</gco:Date>
                           </gmd:date>
                           <gmd:dateType>
                              <gmd:CI_DateTypeCode codeList="https://data.noaa.gov/resources/iso19139/schema/resources/Codelist/gmxCodelists.xml#CI_DateTypeCode"
                                                   codeListValue="revision">revision</gmd:CI_DateTypeCode>
                           </gmd:dateType>
                        </gmd:CI_Date>
                     </gmd:date>
                     <gmd:edition>
                        <gco:CharacterString>Version 8.6</gco:CharacterString>
                     </gmd:edition>
                     <gmd:citedResponsibleParty>
                        <gmd:CI_ResponsibleParty>
                           <gmd:organisationName>
                              <gco:CharacterString>Global Change Data Center, Science and Exploration Directorate, Goddard Space Flight Center (GSFC) National Aeronautics and Space Administration (NASA)</gco:CharacterString>
                           </gmd:organisationName>
                           <gmd:contactInfo>
                              <gmd:CI_Contact>
                                 <gmd:onlineResource>
                                    <gmd:CI_OnlineResource>
                                       <gmd:linkage>
                                          <gmd:URL>https://earthdata.nasa.gov/about/gcmd/global-change-master-directory-gcmd-keywords</gmd:URL>
                                       </gmd:linkage>
                                       <gmd:protocol>
                                          <gco:CharacterString>HTTPS</gco:CharacterString>
                                       </gmd:protocol>
                                       <gmd:applicationProfile>
                                          <gco:CharacterString>Web Browser</gco:CharacterString>
                                       </gmd:applicationProfile>
                                       <gmd:name>
                                          <gco:CharacterString>Global Change Master Directory (GCMD) Keywords</gco:CharacterString>
                                       </gmd:name>
                                       <gmd:description>
                                          <gco:CharacterString>The information provided on this page seeks to define how the GCMD Keywords are structured, used and accessed. It also provides information on how users can participate in the further development of the keywords.</gco:CharacterString>
                                       </gmd:description>
                                       <gmd:function>
                                          <gmd:CI_OnLineFunctionCode codeList="https://data.noaa.gov/resources/iso19139/schema/resources/Codelist/gmxCodelists.xml#CI_OnLineFunctionCode"
                                                                     codeListValue="information">information</gmd:CI_OnLineFunctionCode>
                                       </gmd:function>
                                    </gmd:CI_OnlineResource>
                                 </gmd:onlineResource>
                              </gmd:CI_Contact>
                           </gmd:contactInfo>
                           <gmd:role>
                              <gmd:CI_RoleCode codeList="https://data.noaa.gov/resources/iso19139/schema/resources/Codelist/gmxCodelists.xml#CI_RoleCode"
                                               codeListValue="publisher">publisher</gmd:CI_RoleCode>
                           </gmd:role>
                        </gmd:CI_ResponsibleParty>
                     </gmd:citedResponsibleParty>
                  </gmd:CI_Citation>
               </gmd:thesaurusName>
            </gmd:MD_Keywords>
         </gmd:descriptiveKeywords>
         <gmd:descriptiveKeywords>
            <gmd:MD_Keywords>
               <gmd:keyword>
                  <gco:CharacterString>Meteorological Stations</gco:CharacterString>
               </gmd:keyword>
               <gmd:type>
                  <gmd:MD_KeywordTypeCode codeList="https://data.noaa.gov/resources/iso19139/schema/resources/Codelist/gmxCodelists.xml#MD_KeywordTypeCode"
                                          codeListValue="platform">platform</gmd:MD_KeywordTypeCode>
               </gmd:type>
               <gmd:thesaurusName>
                  <gmd:CI_Citation>
                     <gmd:title>
                        <gco:CharacterString>Global Change Master Directory (GCMD) Platform Keywords</gco:CharacterString>
                     </gmd:title>
                     <gmd:date>
                        <gmd:CI_Date>
                           <gmd:date>
                              <gco:Date>2018</gco:Date>
                           </gmd:date>
                           <gmd:dateType>
                              <gmd:CI_DateTypeCode codeList="https://data.noaa.gov/resources/iso19139/schema/resources/Codelist/gmxCodelists.xml#CI_DateTypeCode"
                                                   codeListValue="revision">revision</gmd:CI_DateTypeCode>
                           </gmd:dateType>
                        </gmd:CI_Date>
                     </gmd:date>
                     <gmd:edition>
                        <gco:CharacterString>Version 8.6</gco:CharacterString>
                     </gmd:edition>
                     <gmd:citedResponsibleParty>
                        <gmd:CI_ResponsibleParty>
                           <gmd:organisationName>
                              <gco:CharacterString>Global Change Data Center, Science and Exploration Directorate, Goddard Space Flight Center (GSFC) National Aeronautics and Space Administration (NASA)</gco:CharacterString>
                           </gmd:organisationName>
                           <gmd:contactInfo>
                              <gmd:CI_Contact>
                                 <gmd:onlineResource>
                                    <gmd:CI_OnlineResource>
                                       <gmd:linkage>
                                          <gmd:URL>https://earthdata.nasa.gov/about/gcmd/global-change-master-directory-gcmd-keywords</gmd:URL>
                                       </gmd:linkage>
                                       <gmd:protocol>
                                          <gco:CharacterString>HTTPS</gco:CharacterString>
                                       </gmd:protocol>
                                       <gmd:applicationProfile>
                                          <gco:CharacterString>Web Browser</gco:CharacterString>
                                       </gmd:applicationProfile>
                                       <gmd:name>
                                          <gco:CharacterString>Global Change Master Directory (GCMD) Keywords</gco:CharacterString>
                                       </gmd:name>
                                       <gmd:description>
                                          <gco:CharacterString>The information provided on this page seeks to define how the GCMD Keywords are structured, used and accessed. It also provides information on how users can participate in the further development of the keywords.</gco:CharacterString>
                                       </gmd:description>
                                       <gmd:function>
                                          <gmd:CI_OnLineFunctionCode codeList="https://data.noaa.gov/resources/iso19139/schema/resources/Codelist/gmxCodelists.xml#CI_OnLineFunctionCode"
                                                                     codeListValue="information">information</gmd:CI_OnLineFunctionCode>
                                       </gmd:function>
                                    </gmd:CI_OnlineResource>
                                 </gmd:onlineResource>
                              </gmd:CI_Contact>
                           </gmd:contactInfo>
                           <gmd:role>
                              <gmd:CI_RoleCode codeList="https://data.noaa.gov/resources/iso19139/schema/resources/Codelist/gmxCodelists.xml#CI_RoleCode"
                                               codeListValue="publisher">publisher</gmd:CI_RoleCode>
                           </gmd:role>
                        </gmd:CI_ResponsibleParty>
                     </gmd:citedResponsibleParty>
                  </gmd:CI_Citation>
               </gmd:thesaurusName>
            </gmd:MD_Keywords>
         </gmd:descriptiveKeywords>
         <gmd:descriptiveKeywords>
            <gmd:MD_Keywords>
               <gmd:keyword>
                  <gco:CharacterString>Thermometers</gco:CharacterString>
               </gmd:keyword>
               <gmd:keyword>
                  <gco:CharacterString>Anemometers</gco:CharacterString>
               </gmd:keyword>
               <gmd:keyword>
                  <gco:CharacterString>Rain Gauges</gco:CharacterString>
               </gmd:keyword>
               <gmd:keyword>
                  <gco:CharacterString>Barometers</gco:CharacterString>
               </gmd:keyword>
               <gmd:keyword>
                  <gco:CharacterString>Visual Observations</gco:CharacterString>
               </gmd:keyword>
               <gmd:type>
                  <gmd:MD_KeywordTypeCode codeList="https://data.noaa.gov/resources/iso19139/schema/resources/Codelist/gmxCodelists.xml#MD_KeywordTypeCode"
                                          codeListValue="instrument">instrument</gmd:MD_KeywordTypeCode>
               </gmd:type>
               <gmd:thesaurusName>
                  <gmd:CI_Citation>
                     <gmd:title>
                        <gco:CharacterString>Global Change Master Directory (GCMD) Instrument Keywords</gco:CharacterString>
                     </gmd:title>
                     <gmd:date>
                        <gmd:CI_Date>
                           <gmd:date>
                              <gco:Date>2018</gco:Date>
                           </gmd:date>
                           <gmd:dateType>
                              <gmd:CI_DateTypeCode codeList="https://data.noaa.gov/resources/iso19139/schema/resources/Codelist/gmxCodelists.xml#CI_DateTypeCode"
                                                   codeListValue="revision">revision</gmd:CI_DateTypeCode>
                           </gmd:dateType>
                        </gmd:CI_Date>
                     </gmd:date>
                     <gmd:edition>
                        <gco:CharacterString>Version 8.6</gco:CharacterString>
                     </gmd:edition>
                     <gmd:citedResponsibleParty>
                        <gmd:CI_ResponsibleParty>
                           <gmd:organisationName>
                              <gco:CharacterString>Global Change Data Center, Science and Exploration Directorate, Goddard Space Flight Center (GSFC) National Aeronautics and Space Administration (NASA)</gco:CharacterString>
                           </gmd:organisationName>
                           <gmd:contactInfo>
                              <gmd:CI_Contact>
                                 <gmd:onlineResource>
                                    <gmd:CI_OnlineResource>
                                       <gmd:linkage>
                                          <gmd:URL>https://earthdata.nasa.gov/about/gcmd/global-change-master-directory-gcmd-keywords</gmd:URL>
                                       </gmd:linkage>
                                       <gmd:protocol>
                                          <gco:CharacterString>HTTPS</gco:CharacterString>
                                       </gmd:protocol>
                                       <gmd:applicationProfile>
                                          <gco:CharacterString>Web Browser</gco:CharacterString>
                                       </gmd:applicationProfile>
                                       <gmd:name>
                                          <gco:CharacterString>Global Change Master Directory (GCMD) Keywords</gco:CharacterString>
                                       </gmd:name>
                                       <gmd:description>
                                          <gco:CharacterString>The information provided on this page seeks to define how the GCMD Keywords are structured, used and accessed. It also provides information on how users can participate in the further development of the keywords.</gco:CharacterString>
                                       </gmd:description>
                                       <gmd:function>
                                          <gmd:CI_OnLineFunctionCode codeList="https://data.noaa.gov/resources/iso19139/schema/resources/Codelist/gmxCodelists.xml#CI_OnLineFunctionCode"
                                                                     codeListValue="information">information</gmd:CI_OnLineFunctionCode>
                                       </gmd:function>
                                    </gmd:CI_OnlineResource>
                                 </gmd:onlineResource>
                              </gmd:CI_Contact>
                           </gmd:contactInfo>
                           <gmd:role>
                              <gmd:CI_RoleCode codeList="https://data.noaa.gov/resources/iso19139/schema/resources/Codelist/gmxCodelists.xml#CI_RoleCode"
                                               codeListValue="publisher">publisher</gmd:CI_RoleCode>
                           </gmd:role>
                        </gmd:CI_ResponsibleParty>
                     </gmd:citedResponsibleParty>
                  </gmd:CI_Citation>
               </gmd:thesaurusName>
            </gmd:MD_Keywords>
         </gmd:descriptiveKeywords>
         <gmd:descriptiveKeywords>
            <gmd:MD_Keywords>
               <gmd:keyword>
                  <gco:CharacterString>DOC/NOAA/NESDIS/NCDC &gt; National Climatic Data Center, NESDIS, NOAA, U.S. Department of Commerce</gco:CharacterString>
               </gmd:keyword>
               <gmd:keyword>
                  <gco:CharacterString>DOC/NOAA/NESDIS/NCEI &gt; National Centers for Environmental Information, NESDIS, NOAA, U.S. Department of Commerce</gco:CharacterString>
               </gmd:keyword>
               <gmd:type>
                  <gmd:MD_KeywordTypeCode codeList="https://data.noaa.gov/resources/iso19139/schema/resources/Codelist/gmxCodelists.xml#MD_KeywordTypeCode"
                                          codeListValue="dataCentre">dataCentre</gmd:MD_KeywordTypeCode>
               </gmd:type>
               <gmd:thesaurusName>
                  <gmd:CI_Citation>
                     <gmd:title>
                        <gco:CharacterString>Global Change Master Directory (GCMD) Data Center Keywords</gco:CharacterString>
                     </gmd:title>
                     <gmd:date>
                        <gmd:CI_Date>
                           <gmd:date>
                              <gco:Date>2018</gco:Date>
                           </gmd:date>
                           <gmd:dateType>
                              <gmd:CI_DateTypeCode codeList="https://data.noaa.gov/resources/iso19139/schema/resources/Codelist/gmxCodelists.xml#CI_DateTypeCode"
                                                   codeListValue="revision">revision</gmd:CI_DateTypeCode>
                           </gmd:dateType>
                        </gmd:CI_Date>
                     </gmd:date>
                     <gmd:edition>
                        <gco:CharacterString>Version 8.6</gco:CharacterString>
                     </gmd:edition>
                     <gmd:citedResponsibleParty>
                        <gmd:CI_ResponsibleParty>
                           <gmd:organisationName>
                              <gco:CharacterString>Global Change Data Center, Science and Exploration Directorate, Goddard Space Flight Center (GSFC) National Aeronautics and Space Administration (NASA)</gco:CharacterString>
                           </gmd:organisationName>
                           <gmd:contactInfo>
                              <gmd:CI_Contact>
                                 <gmd:onlineResource>
                                    <gmd:CI_OnlineResource>
                                       <gmd:linkage>
                                          <gmd:URL>https://earthdata.nasa.gov/about/gcmd/global-change-master-directory-gcmd-keywords</gmd:URL>
                                       </gmd:linkage>
                                       <gmd:protocol>
                                          <gco:CharacterString>HTTPS</gco:CharacterString>
                                       </gmd:protocol>
                                       <gmd:applicationProfile>
                                          <gco:CharacterString>Web Browser</gco:CharacterString>
                                       </gmd:applicationProfile>
                                       <gmd:name>
                                          <gco:CharacterString>Global Change Master Directory (GCMD) Keywords</gco:CharacterString>
                                       </gmd:name>
                                       <gmd:description>
                                          <gco:CharacterString>The information provided on this page seeks to define how the GCMD Keywords are structured, used and accessed. It also provides information on how users can participate in the further development of the keywords.</gco:CharacterString>
                                       </gmd:description>
                                       <gmd:function>
                                          <gmd:CI_OnLineFunctionCode codeList="https://data.noaa.gov/resources/iso19139/schema/resources/Codelist/gmxCodelists.xml#CI_OnLineFunctionCode"
                                                                     codeListValue="information">information</gmd:CI_OnLineFunctionCode>
                                       </gmd:function>
                                    </gmd:CI_OnlineResource>
                                 </gmd:onlineResource>
                              </gmd:CI_Contact>
                           </gmd:contactInfo>
                           <gmd:role>
                              <gmd:CI_RoleCode codeList="https://data.noaa.gov/resources/iso19139/schema/resources/Codelist/gmxCodelists.xml#CI_RoleCode"
                                               codeListValue="publisher">publisher</gmd:CI_RoleCode>
                           </gmd:role>
                        </gmd:CI_ResponsibleParty>
                     </gmd:citedResponsibleParty>
                  </gmd:CI_Citation>
               </gmd:thesaurusName>
            </gmd:MD_Keywords>
         </gmd:descriptiveKeywords>
         <gmd:resourceConstraints>
            <gmd:MD_Constraints>
               <gmd:useLimitation>
                  <gco:CharacterString>Controlled user access to the EV2 system</gco:CharacterString>
               </gmd:useLimitation>
            </gmd:MD_Constraints>
         </gmd:resourceConstraints>
         <gmd:resourceConstraints xlink:title="Distribution Liability">
            <gmd:MD_LegalConstraints xsi:schemaLocation="http://www.isotc211.org/2005/gmi https://data.noaa.gov/resources/iso19139/schema.xsd"
                                     uuid="dadd4ac3-2b9f-4db5-8603-71285b94c3d7">
               <gmd:accessConstraints>
                  <gmd:MD_RestrictionCode codeList="https://data.noaa.gov/resources/iso19139/schema/resources/Codelist/gmxCodelists.xml#MD_RestrictionCode"
                                          codeListValue="otherRestrictions">otherRestrictions</gmd:MD_RestrictionCode>
               </gmd:accessConstraints>
               <gmd:otherConstraints>
                  <gco:CharacterString>Distribution liability: NOAA and NCEI make no warranty, expressed or implied, regarding these data, nor does the fact of distribution constitute such a warranty. NOAA and NCEI cannot assume liability for any damages caused by any errors or omissions in these data. If appropriate, NCEI can only certify that the data it distributes are an authentic copy of the records that were accepted for inclusion in the NCEI archives.</gco:CharacterString>
               </gmd:otherConstraints>
            </gmd:MD_LegalConstraints>
         </gmd:resourceConstraints>
         <gmd:resourceConstraints xlink:title="Use Liability">
            <gmd:MD_LegalConstraints xsi:schemaLocation="http://www.isotc211.org/2005/gmi https://data.noaa.gov/resources/iso19139/schema.xsd"
                                     uuid="e8163b1b-fb5a-4f4e-8d5c-ed06da10e21b">
               <gmd:useConstraints>
                  <gmd:MD_RestrictionCode codeList="https://data.noaa.gov/resources/iso19139/schema/resources/Codelist/gmxCodelists.xml#MD_RestrictionCode"
                                          codeListValue="otherRestrictions">otherRestrictions</gmd:MD_RestrictionCode>
               </gmd:useConstraints>
               <gmd:otherConstraints>
                  <gco:CharacterString>Use liability: NOAA and NCEI cannot provide any warranty as to the accuracy, reliability, or completeness of furnished data. Users assume responsibility to determine the usability of these data. The user is responsible for the results of any application of this data for other than its intended purpose.</gco:CharacterString>
               </gmd:otherConstraints>
            </gmd:MD_LegalConstraints>
         </gmd:resourceConstraints>
         <gmd:spatialRepresentationType>
            <gmd:MD_SpatialRepresentationTypeCode codeList="https://data.noaa.gov/resources/iso19139/schema/resources/Codelist/gmxCodelists.xml#MD_SpatialRepresentationTypeCode"
                                                  codeListValue="textTable">textTable</gmd:MD_SpatialRepresentationTypeCode>
         </gmd:spatialRepresentationType>
         <gmd:spatialResolution gco:nilReason="missing"/>
         <gmd:language>
            <gco:CharacterString>eng; USA</gco:CharacterString>
         </gmd:language>
         <gmd:topicCategory>
            <gmd:MD_TopicCategoryCode>climatologyMeteorologyAtmosphere</gmd:MD_TopicCategoryCode>
         </gmd:topicCategory>
         <gmd:environmentDescription>
            <gco:CharacterString>paper forms</gco:CharacterString>
         </gmd:environmentDescription>
         <gmd:extent>
            <gmd:EX_Extent id="boundingExtent">
               <gmd:description>
                  <gco:CharacterString/>
               </gmd:description>
               <gmd:geographicElement>
                  <gmd:EX_GeographicBoundingBox id="boundingGeographicBoundingBox">
                     <gmd:extentTypeCode>
                        <gco:Boolean>1</gco:Boolean>
                     </gmd:extentTypeCode>
                     <gmd:westBoundLongitude>
                        <gco:Decimal>-70.97</gco:Decimal>
                     </gmd:westBoundLongitude>
                     <gmd:eastBoundLongitude>
                        <gco:Decimal>-70.96</gco:Decimal>
                     </gmd:eastBoundLongitude>
                     <gmd:southBoundLatitude>
                        <gco:Decimal>-53.00</gco:Decimal>
                     </gmd:southBoundLatitude>
                     <gmd:northBoundLatitude>
                        <gco:Decimal>-52.99</gco:Decimal>
                     </gmd:northBoundLatitude>
                  </gmd:EX_GeographicBoundingBox>
               </gmd:geographicElement>
               <gmd:temporalElement>
                  <gmd:EX_TemporalExtent id="boundingTemporalExtent">
                     <gmd:extent>
                        <gml:TimePeriod gml:id="datasetTimePeriod">
                           <gml:description>ground condition</gml:description>
                           <gml:beginPosition>1896</gml:beginPosition>
                           <gml:endPosition>1954</gml:endPosition>
                        </gml:TimePeriod>
                     </gmd:extent>
                  </gmd:EX_TemporalExtent>
               </gmd:temporalElement>
            </gmd:EX_Extent>
         </gmd:extent>
      </gmd:MD_DataIdentification>
   </gmd:identificationInfo>
   <gmd:distributionInfo>
      <gmd:MD_Distribution>
         <gmd:distributor>
            <gmd:MD_Distributor>
               <gmd:distributorContact>
                  <gmd:CI_ResponsibleParty>
                     <gmd:organisationName>
                        <gco:CharacterString>DOC/NOAA/NESDIS/NCEI &gt; National Centers for Environmental Information, NESDIS, NOAA, U.S. Department of Commerce</gco:CharacterString>
                     </gmd:organisationName>
                     <gmd:positionName>
                        <gco:CharacterString>Customer Engagement Branch</gco:CharacterString>
                     </gmd:positionName>
                     <gmd:contactInfo>
                        <gmd:CI_Contact>
                           <gmd:phone>
                              <gmd:CI_Telephone>
                                 <gmd:voice>
                                    <gco:CharacterString>1-828-271-4800</gco:CharacterString>
                                 </gmd:voice>
                                 <gmd:facsimile>
                                    <gco:CharacterString>1-828-271-4876</gco:CharacterString>
                                 </gmd:facsimile>
                              </gmd:CI_Telephone>
                           </gmd:phone>
                           <gmd:address>
                              <gmd:CI_Address>
                                 <gmd:deliveryPoint>
                                    <gco:CharacterString>151 Patton Avenue</gco:CharacterString>
                                 </gmd:deliveryPoint>
                                 <gmd:deliveryPoint>
                                    <gco:CharacterString>Veach-Baley Federal Building, Room 468</gco:CharacterString>
                                 </gmd:deliveryPoint>
                                 <gmd:city>
                                    <gco:CharacterString>Asheville</gco:CharacterString>
                                 </gmd:city>
                                 <gmd:administrativeArea>
                                    <gco:CharacterString>NC</gco:CharacterString>
                                 </gmd:administrativeArea>
                                 <gmd:postalCode>
                                    <gco:CharacterString>28801-5001</gco:CharacterString>
                                 </gmd:postalCode>
                                 <gmd:country>
                                    <gco:CharacterString>USA</gco:CharacterString>
                                 </gmd:country>
                                 <gmd:electronicMailAddress>
                                    <gco:CharacterString>ncei.orders@noaa.gov</gco:CharacterString>
                                 </gmd:electronicMailAddress>
                              </gmd:CI_Address>
                           </gmd:address>
                           <gmd:onlineResource>
                              <gmd:CI_OnlineResource>
                                 <gmd:linkage>
                                    <gmd:URL>https://www.ncei.noaa.gov</gmd:URL>
                                 </gmd:linkage>
                                 <gmd:protocol>
                                    <gco:CharacterString>HTTPS</gco:CharacterString>
                                 </gmd:protocol>
                                 <gmd:applicationProfile>
                                    <gco:CharacterString>Web Browser</gco:CharacterString>
                                 </gmd:applicationProfile>
                                 <gmd:name>
                                    <gco:CharacterString>NOAA National Centers for Environmental Information (NCEI)</gco:CharacterString>
                                 </gmd:name>
                                 <gmd:description>
                                    <gco:CharacterString>NCEI home page with information, data access and contact information.</gco:CharacterString>
                                 </gmd:description>
                                 <gmd:function>
                                    <gmd:CI_OnLineFunctionCode codeList="https://data.noaa.gov/resources/iso19139/schema/resources/Codelist/gmxCodelists.xml#CI_OnLineFunctionCode"
                                                               codeListValue="information">information</gmd:CI_OnLineFunctionCode>
                                 </gmd:function>
                              </gmd:CI_OnlineResource>
                           </gmd:onlineResource>
                           <gmd:hoursOfService>
                              <gco:CharacterString>8:00 - 6:00 Eastern</gco:CharacterString>
                           </gmd:hoursOfService>
                        </gmd:CI_Contact>
                     </gmd:contactInfo>
                     <gmd:role>
                        <gmd:CI_RoleCode codeList="https://data.noaa.gov/resources/iso19139/schema/resources/Codelist/gmxCodelists.xml#CI_RoleCode"
                                         codeListValue="distributor">distributor</gmd:CI_RoleCode>
                     </gmd:role>
                  </gmd:CI_ResponsibleParty>
               </gmd:distributorContact>
               <gmd:distributionOrderProcess>
                  <gmd:MD_StandardOrderProcess>
                     <gmd:fees>
                        <gco:CharacterString>In most cases, electronic downloads of the data are free, however fees may apply for data certifications, copies of analog materials, and data distribution on physical media.</gco:CharacterString>
                     </gmd:fees>
                  </gmd:MD_StandardOrderProcess>
               </gmd:distributionOrderProcess>
               <gmd:distributorFormat>
                  <gmd:MD_Format>
                     <gmd:name>
                        <gco:CharacterString>XML</gco:CharacterString>
                     </gmd:name>
                     <gmd:version gco:nilReason="missing"/>
                  </gmd:MD_Format>
               </gmd:distributorFormat>
               <gmd:distributorTransferOptions>
                  <gmd:MD_DigitalTransferOptions>
                     <gmd:transferSize>
                        <gco:Real>1</gco:Real>
                     </gmd:transferSize>
                     <gmd:onLine>
                        <gmd:CI_OnlineResource>
                           <gmd:linkage>
                              <gmd:URL>https://data.nodc.noaa.gov/cgi-bin/iso?id=gov.noaa.ncdc:C01088</gmd:URL>
                           </gmd:linkage>
                           <gmd:protocol>
                              <gco:CharacterString>HTTPS</gco:CharacterString>
                           </gmd:protocol>
                           <gmd:applicationProfile>
                              <gco:CharacterString>Description</gco:CharacterString>
                           </gmd:applicationProfile>
                           <gmd:name>
                              <gco:CharacterString>Surface Observations from Punta Arenas, Chile Landing Page</gco:CharacterString>
                           </gmd:name>
                           <gmd:description>
                              <gco:CharacterString>Dataset landing page with general information and access links for the dataset.</gco:CharacterString>
                           </gmd:description>
                           <gmd:function>
                              <gmd:CI_OnLineFunctionCode codeList="https://data.noaa.gov/resources/iso19139/schema/resources/Codelist/gmxCodelists.xml#CI_OnLineFunctionCode"
                                                         codeListValue="information">information</gmd:CI_OnLineFunctionCode>
                           </gmd:function>
                        </gmd:CI_OnlineResource>
                     </gmd:onLine>
                  </gmd:MD_DigitalTransferOptions>
               </gmd:distributorTransferOptions>
            </gmd:MD_Distributor>
         </gmd:distributor>
         <gmd:distributor>
            <gmd:MD_Distributor>
               <gmd:distributorContact>
                  <gmd:CI_ResponsibleParty>
                     <gmd:organisationName>
                        <gco:CharacterString>DOC/NOAA/NESDIS/NCEI &gt; National Centers for Environmental Information, NESDIS, NOAA, U.S. Department of Commerce</gco:CharacterString>
                     </gmd:organisationName>
                     <gmd:positionName>
                        <gco:CharacterString>Customer Engagement Branch</gco:CharacterString>
                     </gmd:positionName>
                     <gmd:contactInfo>
                        <gmd:CI_Contact>
                           <gmd:phone>
                              <gmd:CI_Telephone>
                                 <gmd:voice>
                                    <gco:CharacterString>1-828-271-4800</gco:CharacterString>
                                 </gmd:voice>
                                 <gmd:facsimile>
                                    <gco:CharacterString>1-828-271-4876</gco:CharacterString>
                                 </gmd:facsimile>
                              </gmd:CI_Telephone>
                           </gmd:phone>
                           <gmd:address>
                              <gmd:CI_Address>
                                 <gmd:deliveryPoint>
                                    <gco:CharacterString>151 Patton Avenue</gco:CharacterString>
                                 </gmd:deliveryPoint>
                                 <gmd:deliveryPoint>
                                    <gco:CharacterString>Veach-Baley Federal Building, Room 468</gco:CharacterString>
                                 </gmd:deliveryPoint>
                                 <gmd:city>
                                    <gco:CharacterString>Asheville</gco:CharacterString>
                                 </gmd:city>
                                 <gmd:administrativeArea>
                                    <gco:CharacterString>NC</gco:CharacterString>
                                 </gmd:administrativeArea>
                                 <gmd:postalCode>
                                    <gco:CharacterString>28801-5001</gco:CharacterString>
                                 </gmd:postalCode>
                                 <gmd:country>
                                    <gco:CharacterString>USA</gco:CharacterString>
                                 </gmd:country>
                                 <gmd:electronicMailAddress>
                                    <gco:CharacterString>ncei.orders@noaa.gov</gco:CharacterString>
                                 </gmd:electronicMailAddress>
                              </gmd:CI_Address>
                           </gmd:address>
                           <gmd:onlineResource>
                              <gmd:CI_OnlineResource>
                                 <gmd:linkage>
                                    <gmd:URL>https://www.ncei.noaa.gov</gmd:URL>
                                 </gmd:linkage>
                                 <gmd:protocol>
                                    <gco:CharacterString>HTTPS</gco:CharacterString>
                                 </gmd:protocol>
                                 <gmd:applicationProfile>
                                    <gco:CharacterString>Web Browser</gco:CharacterString>
                                 </gmd:applicationProfile>
                                 <gmd:name>
                                    <gco:CharacterString>NOAA National Centers for Environmental Information (NCEI)</gco:CharacterString>
                                 </gmd:name>
                                 <gmd:description>
                                    <gco:CharacterString>NCEI home page with information, data access and contact information.</gco:CharacterString>
                                 </gmd:description>
                                 <gmd:function>
                                    <gmd:CI_OnLineFunctionCode codeList="https://data.noaa.gov/resources/iso19139/schema/resources/Codelist/gmxCodelists.xml#CI_OnLineFunctionCode"
                                                               codeListValue="information">information</gmd:CI_OnLineFunctionCode>
                                 </gmd:function>
                              </gmd:CI_OnlineResource>
                           </gmd:onlineResource>
                           <gmd:hoursOfService>
                              <gco:CharacterString>8:00 - 6:00 Eastern</gco:CharacterString>
                           </gmd:hoursOfService>
                        </gmd:CI_Contact>
                     </gmd:contactInfo>
                     <gmd:role>
                        <gmd:CI_RoleCode codeList="https://data.noaa.gov/resources/iso19139/schema/resources/Codelist/gmxCodelists.xml#CI_RoleCode"
                                         codeListValue="distributor">distributor</gmd:CI_RoleCode>
                     </gmd:role>
                  </gmd:CI_ResponsibleParty>
               </gmd:distributorContact>
               <gmd:distributionOrderProcess>
                  <gmd:MD_StandardOrderProcess>
                     <gmd:fees>
                        <gco:CharacterString>In most cases, electronic downloads of the data are free, however fees may apply for data certifications, copies of analog materials, and data distribution on physical media.</gco:CharacterString>
                     </gmd:fees>
                  </gmd:MD_StandardOrderProcess>
               </gmd:distributionOrderProcess>
               <gmd:distributorFormat>
                  <gmd:MD_Format>
                     <gmd:name>
                        <gco:CharacterString>PDF</gco:CharacterString>
                     </gmd:name>
                     <gmd:version gco:nilReason="missing"/>
                     <gmd:specification>
                        <gco:CharacterString/>
                     </gmd:specification>
                     <gmd:fileDecompressionTechnique>
                        <gco:CharacterString/>
                     </gmd:fileDecompressionTechnique>
                  </gmd:MD_Format>
               </gmd:distributorFormat>
               <gmd:distributorTransferOptions>
                  <gmd:MD_DigitalTransferOptions>
                     <gmd:transferSize gco:nilReason="missing"/>
                     <gmd:onLine>
                        <gmd:CI_OnlineResource>
                           <gmd:linkage>
                              <gmd:URL>https://www.ncdc.noaa.gov/EdadsV2/</gmd:URL>
                           </gmd:linkage>
                           <gmd:protocol>
                              <gco:CharacterString>HTTPS</gco:CharacterString>
                           </gmd:protocol>
                           <gmd:applicationProfile>
                              <gco:CharacterString>Information</gco:CharacterString>
                           </gmd:applicationProfile>
                           <gmd:name>
                              <gco:CharacterString>EV2 Image Access System</gco:CharacterString>
                           </gmd:name>
                           <gmd:description>
                              <gco:CharacterString>EV2 Information and Data Access Page</gco:CharacterString>
                           </gmd:description>
                           <gmd:function>
                              <gmd:CI_OnLineFunctionCode codeList="https://data.noaa.gov/resources/iso19139/schema/resources/Codelist/gmxCodelists.xml#CI_OnLineFunctionCode"
                                                         codeListValue="download">download</gmd:CI_OnLineFunctionCode>
                           </gmd:function>
                        </gmd:CI_OnlineResource>
                     </gmd:onLine>
                  </gmd:MD_DigitalTransferOptions>
               </gmd:distributorTransferOptions>
            </gmd:MD_Distributor>
         </gmd:distributor>
      </gmd:MD_Distribution>
   </gmd:distributionInfo>
   <gmd:dataQualityInfo>
      <gmd:DQ_DataQuality>
         <gmd:scope>
            <gmd:DQ_Scope id="datasetScope">
               <gmd:level>
                  <gmd:MD_ScopeCode codeList="https://data.noaa.gov/resources/iso19139/schema/resources/Codelist/gmxCodelists.xml#MD_ScopeCode"
                                    codeListValue="dataset"/>
               </gmd:level>
               <gmd:extent xlink:href="#boundingExtent"/>
            </gmd:DQ_Scope>
         </gmd:scope>
         <gmd:lineage>
            <gmd:LI_Lineage>
               <gmd:statement>
                  <gco:CharacterString>The vast majority of the digital image records available originate from the NCDC physical archives through the Climate Database Modernization Program (CDMP). These efforts produced over 50 million images from 2000-2011. Additional limited scanning activities at NCDC also contribute to the image repository. Partnerships with other NOAA line offices and international weather services have contributed to the broad and global nature of digitally imaged records available from the NCDC.</gco:CharacterString>
               </gmd:statement>
               <gmd:processStep>
                  <gmi:LE_ProcessStep id="ps001">
                     <gmd:description>
                        <gco:CharacterString>Scan</gco:CharacterString>
                     </gmd:description>
                     <gmd:rationale>
                        <gco:CharacterString>To digitize collection in order to make available online.</gco:CharacterString>
                     </gmd:rationale>
                     <gmd:dateTime gco:nilReason="missing"/>
                     <gmd:processor>
                        <gmd:CI_ResponsibleParty>
                           <gmd:organisationName>
                              <gco:CharacterString>NCDC Climate Data Modernization Program</gco:CharacterString>
                           </gmd:organisationName>
                           <gmd:role>
                              <gmd:CI_RoleCode codeList="https://data.noaa.gov/resources/iso19139/schema/resources/Codelist/gmxCodelists.xml#CI_RoleCode"
                                               codeListValue="processor">processor</gmd:CI_RoleCode>
                           </gmd:role>
                        </gmd:CI_ResponsibleParty>
                     </gmd:processor>
                     <gmi:processingInformation gco:nilReason="missing"/>
                  </gmi:LE_ProcessStep>
               </gmd:processStep>
            </gmd:LI_Lineage>
         </gmd:lineage>
      </gmd:DQ_DataQuality>
   </gmd:dataQualityInfo>
   <gmd:dataQualityInfo>
      <gmd:DQ_DataQuality>
         <gmd:scope>
            <gmd:DQ_Scope>
               <gmd:level>
                  <gmd:MD_ScopeCode codeList="https://data.noaa.gov/resources/iso19139/schema/resources/Codelist/gmxCodelists.xml#MD_ScopeCode"
                                    codeListValue="repository">repository</gmd:MD_ScopeCode>
               </gmd:level>
               <gmd:levelDescription>
                  <gmd:MD_ScopeDescription>
                     <gmd:other>
                        <gco:CharacterString>NOAA National Centers for Environmental Information</gco:CharacterString>
                     </gmd:other>
                  </gmd:MD_ScopeDescription>
               </gmd:levelDescription>
            </gmd:DQ_Scope>
         </gmd:scope>
         <gmd:lineage>
            <gmd:LI_Lineage>
               <gmd:processStep>
                  <gmi:LE_ProcessStep>
                     <gmd:description>
                        <gco:CharacterString>NOAA created the National Centers for Environmental Information (NCEI) by merging NOAA's National Climatic Data Center (NCDC), National Geophysical Data Center (NGDC), and National Oceanographic Data Center (NODC), including the National Coastal Data Development Center (NCDDC), per the Consolidated and Further Continuing Appropriations Act, 2015, Public Law 113-235. NCEI launched publicly on April 22, 2015.</gco:CharacterString>
                     </gmd:description>
                     <gmd:dateTime>
                        <gco:DateTime>2015-04-22T00:00:00</gco:DateTime>
                     </gmd:dateTime>
                  </gmi:LE_ProcessStep>
               </gmd:processStep>
            </gmd:LI_Lineage>
         </gmd:lineage>
      </gmd:DQ_DataQuality>
   </gmd:dataQualityInfo>
   <gmd:metadataMaintenance>
      <gmd:MD_MaintenanceInformation>
         <gmd:maintenanceAndUpdateFrequency>
            <gmd:MD_MaintenanceFrequencyCode codeList="https://data.noaa.gov/resources/iso19139/schema/resources/Codelist/gmxCodelists.xml#MD_MaintenanceFrequencyCode"
                                             codeListValue="asNeeded">asNeeded</gmd:MD_MaintenanceFrequencyCode>
         </gmd:maintenanceAndUpdateFrequency>
         <gmd:maintenanceNote>
            <gco:CharacterString>Bulk metadata change applied on 2018-05-25. See version control repository history for metadata change details.</gco:CharacterString>
         </gmd:maintenanceNote>
      </gmd:MD_MaintenanceInformation>
   </gmd:metadataMaintenance>
</gmi:MI_Metadata>
